{
  "_format": "hh-sol-cache-2",
  "files": {
    "D:\\vote-block\\Election-Portal-Pilot\\frontend-admin\\contracts\\addHostelPollsA.sol": {
      "lastModificationDate": 1674970380535,
      "contentHash": "fd90b922f955f892d6cbefee68e98d1b",
      "sourceName": "contracts/addHostelPollsA.sol",
      "solcConfig": {
        "version": "0.7.0",
        "settings": {
          "optimizer": {
            "enabled": false,
            "runs": 200
          },
          "outputSelection": {
            "*": {
              "*": [
                "abi",
                "evm.bytecode",
                "evm.deployedBytecode",
                "evm.methodIdentifiers",
                "metadata"
              ],
              "": [
                "ast"
              ]
            }
          }
        }
      },
      "imports": [
        "../contracts/preElection.sol"
      ],
      "versionPragmas": [
        "^0.7.0"
      ],
      "artifacts": [
        "AddHostelPollsA"
      ]
    },
    "D:\\vote-block\\Election-Portal-Pilot\\frontend-admin\\contracts\\preElection.sol": {
      "lastModificationDate": 1677070581746,
      "contentHash": "4d092253d7df4480d7c41750bd9de485",
      "sourceName": "contracts/preElection.sol",
      "solcConfig": {
        "version": "0.7.0",
        "settings": {
          "optimizer": {
            "enabled": false,
            "runs": 200
          },
          "outputSelection": {
            "*": {
              "*": [
                "abi",
                "evm.bytecode",
                "evm.deployedBytecode",
                "evm.methodIdentifiers",
                "metadata"
              ],
              "": [
                "ast"
              ]
            }
          }
        }
      },
      "imports": [],
      "versionPragmas": [
        "^0.7.0"
      ],
      "artifacts": [
        "PreElection"
      ]
    },
    "D:\\vote-block\\Election-Portal-Pilot\\frontend-admin\\contracts\\election.sol": {
      "lastModificationDate": 1677070565566,
      "contentHash": "2fa2dbccea886f21ee1cd17df8c984f6",
      "sourceName": "contracts/election.sol",
      "solcConfig": {
        "version": "0.7.0",
        "settings": {
          "optimizer": {
            "enabled": false,
            "runs": 200
          },
          "outputSelection": {
            "*": {
              "*": [
                "abi",
                "evm.bytecode",
                "evm.deployedBytecode",
                "evm.methodIdentifiers",
                "metadata"
              ],
              "": [
                "ast"
              ]
            }
          }
        }
      },
      "imports": [
        "../contracts/preElection.sol",
        "../contracts/addHostelPollsA.sol",
        "../contracts/addHostelPollsB.sol",
        "../contracts/addHostelPollsC.sol",
        "../contracts/addHostelPollsD.sol",
        "../contracts/addOtherPolls.sol"
      ],
      "versionPragmas": [
        "^0.7.0"
      ],
      "artifacts": [
        "Election"
      ]
    },
    "D:\\vote-block\\Election-Portal-Pilot\\frontend-admin\\contracts\\addHostelPollsB.sol": {
      "lastModificationDate": 1674970398024,
      "contentHash": "603c3420358c029f76920fb6819c24bd",
      "sourceName": "contracts/addHostelPollsB.sol",
      "solcConfig": {
        "version": "0.7.0",
        "settings": {
          "optimizer": {
            "enabled": false,
            "runs": 200
          },
          "outputSelection": {
            "*": {
              "*": [
                "abi",
                "evm.bytecode",
                "evm.deployedBytecode",
                "evm.methodIdentifiers",
                "metadata"
              ],
              "": [
                "ast"
              ]
            }
          }
        }
      },
      "imports": [
        "../contracts/preElection.sol"
      ],
      "versionPragmas": [
        "^0.7.0"
      ],
      "artifacts": [
        "AddHostelPollsB"
      ]
    },
    "D:\\vote-block\\Election-Portal-Pilot\\frontend-admin\\contracts\\addHostelPollsC.sol": {
      "lastModificationDate": 1674970418023,
      "contentHash": "e2525e9d330ecabb319ea7db3171157d",
      "sourceName": "contracts/addHostelPollsC.sol",
      "solcConfig": {
        "version": "0.7.0",
        "settings": {
          "optimizer": {
            "enabled": false,
            "runs": 200
          },
          "outputSelection": {
            "*": {
              "*": [
                "abi",
                "evm.bytecode",
                "evm.deployedBytecode",
                "evm.methodIdentifiers",
                "metadata"
              ],
              "": [
                "ast"
              ]
            }
          }
        }
      },
      "imports": [
        "../contracts/preElection.sol"
      ],
      "versionPragmas": [
        "^0.7.0"
      ],
      "artifacts": [
        "AddHostelPollsC"
      ]
    },
    "D:\\vote-block\\Election-Portal-Pilot\\frontend-admin\\contracts\\addHostelPollsD.sol": {
      "lastModificationDate": 1674970446511,
      "contentHash": "cb12d44b347c408125697c0a5a69e358",
      "sourceName": "contracts/addHostelPollsD.sol",
      "solcConfig": {
        "version": "0.7.0",
        "settings": {
          "optimizer": {
            "enabled": false,
            "runs": 200
          },
          "outputSelection": {
            "*": {
              "*": [
                "abi",
                "evm.bytecode",
                "evm.deployedBytecode",
                "evm.methodIdentifiers",
                "metadata"
              ],
              "": [
                "ast"
              ]
            }
          }
        }
      },
      "imports": [
        "../contracts/preElection.sol"
      ],
      "versionPragmas": [
        "^0.7.0"
      ],
      "artifacts": [
        "AddHostelPollsD"
      ]
    },
    "D:\\vote-block\\Election-Portal-Pilot\\frontend-admin\\contracts\\addOtherPolls.sol": {
      "lastModificationDate": 1677070531873,
      "contentHash": "a6b358442eac90c5562eef34df87ac2d",
      "sourceName": "contracts/addOtherPolls.sol",
      "solcConfig": {
        "version": "0.7.0",
        "settings": {
          "optimizer": {
            "enabled": false,
            "runs": 200
          },
          "outputSelection": {
            "*": {
              "*": [
                "abi",
                "evm.bytecode",
                "evm.deployedBytecode",
                "evm.methodIdentifiers",
                "metadata"
              ],
              "": [
                "ast"
              ]
            }
          }
        }
      },
      "imports": [
        "../contracts/preElection.sol"
      ],
      "versionPragmas": [
        "^0.7.0"
      ],
      "artifacts": [
        "AddOtherPolls"
      ]
    }
  }
}
